Myexample.cp312-win_amd64.pyd
Myexample-2.0.dist-info/LICENSE
Myexample-2.0.dist-info/METADATA
Myexample-2.0.dist-info/WHEEL
Myexample-2.0.dist-info/top_level.txt
Myexample-2.0.dist-info/RECORD
