Metadata-Version: 2.1
Name: Myexample
Version: 2.0
Summary: Example package with C++ extension
Home-page: https://github.com/lfpu
Author: lfpu
Author-email: pulongfei@outlook.com
Classifier: Programming Language :: Python :: 3
Classifier: License :: OSI Approved :: MIT License
Classifier: Operating System :: OS Independent
License-File: LICENSE
